jdmtool/__init__.py
jdmtool/avidyne.py
jdmtool/chartview.py
jdmtool/checksum.py
jdmtool/common.py
jdmtool/config.py
jdmtool/const.py
jdmtool/dbf.py
jdmtool/downloader.py
jdmtool/featunlk.py
jdmtool/main.py
jdmtool/service.py
jdmtool/taw.py
jdmtool/data_card/__init__.py
jdmtool/data_card/common.py
jdmtool/data_card/detect.py
jdmtool/data_card/garmin.py
jdmtool/data_card/skybound.py
jdmtool/data_card/firmware/grmn0300.dat
jdmtool/data_card/firmware/grmn0500.dat
jdmtool/data_card/firmware/grmn1300.dat
jdmtool-0.5.1.dist-info/licenses/LICENSE
jdmtool-0.5.1.dist-info/METADATA
jdmtool-0.5.1.dist-info/WHEEL
jdmtool-0.5.1.dist-info/entry_points.txt
jdmtool-0.5.1.dist-info/top_level.txt
jdmtool-0.5.1.dist-info/RECORD
