Metadata-Version: 2.4
Name: jdmtool
Version: 0.5.1
Summary: Tool for downloading and transferring Jeppesen databases
Author-email: Dima Ryazanov <dima@gmail.com>
Project-URL: Homepage, https://github.com/dimaryaz/jdmtool
Project-URL: Issues, https://github.com/dimaryaz/jdmtool/issues
Project-URL: Changelog, https://github.com/dimaryaz/jdmtool/blob/main/CHANGELOG.md
Classifier: Programming Language :: Python :: 3
Classifier: License :: OSI Approved :: Apache Software License
Classifier: Operating System :: OS Independent
Requires-Python: >=3.9
License-File: LICENSE
Requires-Dist: platformdirs>=2.6.2
Requires-Dist: psutil>=5.9.4
Requires-Dist: pyudev>=0.24.3; sys_platform == "linux"
Requires-Dist: pywin32>=306; sys_platform == "win32"
Requires-Dist: requests>=2.26.0
Requires-Dist: tqdm>=4.1.0
Requires-Dist: typing_extensions; python_version < "3.11"
Provides-Extra: jit
Requires-Dist: numpy>=1.21.6; extra == "jit"
Requires-Dist: numba>=0.56.4; extra == "jit"
Provides-Extra: usb
Requires-Dist: libusb1>=2.0.1; extra == "usb"
Dynamic: license-file
